durable_network_x/__init__.py
durable_network_x/durable_digraph.py
durable_network_x/durable_graph.py
durable_network_x/durable_multi_digraph.py
durable_network_x/durable_multi_graph.py
durable_network_x/storage_managers/__init__.py
durable_network_x/storage_managers/local_file_storage_manager.py
durable_network_x/storage_managers/s3_storage_manager.py
durable_network_x-0.1.1.dist-info/LICENSE.md
durable_network_x-0.1.1.dist-info/METADATA
durable_network_x-0.1.1.dist-info/WHEEL
durable_network_x-0.1.1.dist-info/RECORD
