Metadata-Version: 2.1
Name: durable-network-x
Version: 0.1.1
Summary: This is the durable NetworkX wrapper
Author: Saad Ahmad
Author-email: saadkwi12@hotmail.com
Requires-Python: >=3.9,<4.0
Classifier: Programming Language :: Python :: 3
Classifier: Programming Language :: Python :: 3.9
Classifier: Programming Language :: Python :: 3.10
Classifier: Programming Language :: Python :: 3.11
Requires-Dist: dataclasses-json (>=0.6.1,<0.7.0)
Requires-Dist: networkx (>=3.2,<4.0)
